src/robotcode/cli/__init__.py
src/robotcode/cli/__main__.py
src/robotcode/cli/__version__.py
src/robotcode/cli/py.typed
src/robotcode/cli/commands/__init__.py
src/robotcode/cli/commands/config.py
src/robotcode/cli/commands/profiles.py
robotcode-2.0.0.dist-info/METADATA
robotcode-2.0.0.dist-info/WHEEL
robotcode-2.0.0.dist-info/entry_points.txt
robotcode-2.0.0.dist-info/licenses/LICENSE.txt
robotcode-2.0.0.dist-info/RECORD
