Metadata-Version: 2.4
Name: robotcode
Version: 2.0.0
Summary: Command line interface for RobotCode
Project-URL: Homepage, https://robotcode.io
Project-URL: Donate, https://opencollective.com/robotcode
Project-URL: Documentation, https://github.com/robotcodedev/robotcode#readme
Project-URL: Changelog, https://github.com/robotcodedev/robotcode/blob/main/CHANGELOG.md
Project-URL: Issues, https://github.com/robotcodedev/robotcode/issues
Project-URL: Source, https://github.com/robotcodedev/robotcode
Author-email: Daniel Biehl <dbiehl@live.de>
License: Apache-2.0
License-File: LICENSE.txt
Keywords: Acceptance Test Driven Development,Acceptance Testing,BDD,BDT,Behavior Driven Testing,Data Driven,Debug Adapter Protocol,Keyword Driven,Language Server Protocol,RPA,RobotFramework,Robotic Process Automation,Test,Testing,Visual Studio Code
Classifier: Development Status :: 5 - Production/Stable
Classifier: Framework :: Robot Framework
Classifier: Framework :: Robot Framework :: Tool
Classifier: Intended Audience :: Developers
Classifier: License :: OSI Approved :: Apache Software License
Classifier: Operating System :: OS Independent
Classifier: Programming Language :: Python :: 3.10
Classifier: Programming Language :: Python :: 3.11
Classifier: Programming Language :: Python :: 3.12
Classifier: Programming Language :: Python :: 3.13
Classifier: Programming Language :: Python :: 3.14
Classifier: Programming Language :: Python :: Implementation :: CPython
Classifier: Topic :: Software Development :: Debuggers
Classifier: Topic :: Software Development :: Quality Assurance
Classifier: Topic :: Software Development :: Testing
Classifier: Topic :: Software Development :: Testing :: Acceptance
Classifier: Topic :: Software Development :: Testing :: BDD
Classifier: Topic :: Text Editors :: Integrated Development Environments (IDE)
Classifier: Topic :: Utilities
Classifier: Typing :: Typed
Requires-Python: >=3.10
Requires-Dist: robotcode-core==2.0.0
Requires-Dist: robotcode-plugin==2.0.0
Requires-Dist: robotcode-robot==2.0.0
Provides-Extra: all
Requires-Dist: docutils; extra == 'all'
Requires-Dist: pyyaml>=5.4; extra == 'all'
Requires-Dist: rich; extra == 'all'
Requires-Dist: robotcode-analyze==2.0.0; extra == 'all'
Requires-Dist: robotcode-debugger==2.0.0; extra == 'all'
Requires-Dist: robotcode-language-server==2.0.0; extra == 'all'
Requires-Dist: robotcode-repl-server==2.0.0; extra == 'all'
Requires-Dist: robotcode-repl==2.0.0; extra == 'all'
Requires-Dist: robotcode-runner==2.0.0; extra == 'all'
Requires-Dist: robotframework-robocop>=2.0.0; extra == 'all'
Provides-Extra: analyze
Requires-Dist: robotcode-analyze==2.0.0; extra == 'analyze'
Provides-Extra: colored
Requires-Dist: rich; extra == 'colored'
Provides-Extra: debugger
Requires-Dist: robotcode-debugger==2.0.0; extra == 'debugger'
Provides-Extra: languageserver
Requires-Dist: robotcode-language-server==2.0.0; extra == 'languageserver'
Provides-Extra: lint
Requires-Dist: robotframework-robocop>=2.0.0; extra == 'lint'
Provides-Extra: repl
Requires-Dist: robotcode-repl==2.0.0; extra == 'repl'
Provides-Extra: replserver
Requires-Dist: robotcode-repl-server==2.0.0; extra == 'replserver'
Provides-Extra: rest
Requires-Dist: docutils; extra == 'rest'
Provides-Extra: runner
Requires-Dist: robotcode-runner==2.0.0; extra == 'runner'
Provides-Extra: yaml
Requires-Dist: pyyaml>=5.4; extra == 'yaml'
